odoo/addons/account_lock_to_date/README.rst
odoo/addons/account_lock_to_date/__init__.py
odoo/addons/account_lock_to_date/__manifest__.py
odoo/addons/account_lock_to_date/i18n/account_lock_to_date.pot
odoo/addons/account_lock_to_date/i18n/it.po
odoo/addons/account_lock_to_date/models/__init__.py
odoo/addons/account_lock_to_date/models/account_move.py
odoo/addons/account_lock_to_date/models/res_company.py
odoo/addons/account_lock_to_date/readme/CONTRIBUTORS.rst
odoo/addons/account_lock_to_date/readme/DESCRIPTION.rst
odoo/addons/account_lock_to_date/readme/USAGE.rst
odoo/addons/account_lock_to_date/static/description/icon.png
odoo/addons/account_lock_to_date/static/description/index.html
odoo/addons/account_lock_to_date/tests/__init__.py
odoo/addons/account_lock_to_date/tests/test_account_lock_to_date_update.py
odoo/addons/account_lock_to_date/wizards/__init__.py
odoo/addons/account_lock_to_date/wizards/account_update_lock_to_date.py
odoo/addons/account_lock_to_date/wizards/account_update_lock_to_date.xml
odoo12_addon_account_lock_to_date-12.0.1.0.0.99.dev13.dist-info/METADATA
odoo12_addon_account_lock_to_date-12.0.1.0.0.99.dev13.dist-info/WHEEL
odoo12_addon_account_lock_to_date-12.0.1.0.0.99.dev13.dist-info/top_level.txt
odoo12_addon_account_lock_to_date-12.0.1.0.0.99.dev13.dist-info/RECORD
